simplechatgpt/__init__.py
simplechatgpt/chat.py
simplechatgpt-1.2.0.dist-info/LICENSE.txt
simplechatgpt-1.2.0.dist-info/METADATA
simplechatgpt-1.2.0.dist-info/WHEEL
simplechatgpt-1.2.0.dist-info/RECORD
