Metadata-Version: 2.1
Name: simplechatgpt
Version: 1.2.0
Summary: An extremely simple interface to ChatGPT
Home-page: https://github.com/Thomas-McKanna/simplechatgpt
License: MIT
Author: Thomas McKanna
Author-email: thomasmckanna@proton.me
Requires-Python: >=3.10,<4.0
Classifier: License :: OSI Approved :: MIT License
Classifier: Programming Language :: Python :: 3
Classifier: Programming Language :: Python :: 3.10
Classifier: Programming Language :: Python :: 3.11
Requires-Dist: dependency (>=0.0.3,<0.0.4)
Requires-Dist: openai
